power_law/__init__.py
power_law/__main__.py
power_law/coins/__init__.py
power_law/coins/bitcoin.py
power_law/coins/common_coin.py
power_law/coins/ethereum.py
power_law/coins/kaspa.py
power_law/config/__init__.py
power_law/config/config.py
power_law/config/config.yaml
power_law/data/__init__.py
power_law/data/data_formatter.py
power_law/data/btc/btcusd_01-08-2024_till_now.json
power_law/data/btc/btcusd_17-06-2010_31-07-2024.json
power_law/data/eth/ethusd_01-08-2024_till_now.json
power_law/data/eth/ethusd_08-08-2015_31-07-2024.json
power_law/data/kas/kasusd_01-08-2024_till_now.json
power_law/data/kas/kasusd_08-05-2022_31-07-2024.json
power_law/price_update/__init__.py
power_law/price_update/coin_api.py
power_law/price_update/coinapi_license.txt
power_law/trendline/__init__.py
power_law/trendline/decreasing_trendline.py
power_law/trendline/power_law_math.py
power_law/trendline/regression.py
power_law/trendline/trendline.py
power_law/visualization/__init__.py
power_law/visualization/colormap.py
power_law/visualization/common_plotter.py
power_law/visualization/plotter.py
power_law/visualization/regression_over_time.py
power_law/visualization/yoy_roi.py
pow_law-1.0.3.dist-info/LICENSE
pow_law-1.0.3.dist-info/METADATA
pow_law-1.0.3.dist-info/WHEEL
pow_law-1.0.3.dist-info/entry_points.txt
pow_law-1.0.3.dist-info/top_level.txt
pow_law-1.0.3.dist-info/RECORD
