Metadata-Version: 2.1
Name: pow-law
Version: 1.0.3
Summary: This Python tool can visualize e.g. the Bitcoin and Kaspa price together with their power law price channels.
Home-page: https://github.com/Chancellor-1/power_law
Author: Chancellor
Author-email: chancelloratbrinkofbailout@gmail.com
Requires-Python: >=3.8.2, <3.13
License-File: LICENSE
Requires-Dist: matplotlib >=3.5.0
Requires-Dist: coinapi.rest.v1 >=1.3
Requires-Dist: pyyaml >=6.0
Requires-Dist: scikit-learn <1.4,>=1.0
Requires-Dist: zipp >=3.20
Requires-Dist: ipykernel >=6.1.0
